[{"country_code":"966","country_iso":"sa","country_name":"Saudi Arabia","created":"0001-01-01T00:00:00Z","minimum_digits":1000000,"maximum_digits":999999999,"login_channels":["whatsapp"],"currency":"ر.س","flag":"https://onsite.fra1.cdn.digitaloceanspaces.com/countryflag/Saudi_Arabia.png","tax_slabs":[0,15],"tax_display_name":"VAT Number","tax_value_display_name":"VAT","published":1,"decimal_digit":6,"timezone":"+03:00"},{"country_code":"971","country_iso":"ae","country_name":"United Arab Emirates","created":"0001-01-01T00:00:00Z","minimum_digits":1000000,"maximum_digits":999999999,"login_channels":["whatsapp"],"currency":"AED","flag":"https://onsite.fra1.cdn.digitaloceanspaces.com/countryflag/United_Arab_Emirates.png","tax_slabs":[5,0],"tax_display_name":"TRN","tax_value_display_name":"VAT","published":1,"decimal_digit":6,"timezone":"+04:00"},{"country_code":"977","country_iso":"np","country_name":"Nepal","created":"0001-01-01T00:00:00Z","minimum_digits":1000000000,"maximum_digits":9999999999,"login_channels":["whatsapp"],"currency":"रू","flag":"https://onsite.fra1.digitaloceanspaces.com/countryflag/Nepal.png","tax_slabs":[0,13],"tax_display_name":"VAT","tax_value_display_name":"VAT","published":1,"decimal_digit":6,"timezone":"+05:45"},{"country_code":"91","country_iso":"in","country_name":"India","created":"0001-01-01T00:00:00Z","minimum_digits":1000000000,"maximum_digits":9999999999,"login_channels":["sms","whatsapp"],"currency":"₹","flag":"https://onsite.fra1.digitaloceanspaces.com/countryflag/India.png","tax_slabs":[18,12,5,0,9,28,0.1,0.25,1.5,3,6,7.5,14,8.9],"tax_display_name":"GST","tax_value_display_name":"GST","published":1,"decimal_digit":6,"timezone":"+05:30"},{"country_code":"974","country_iso":"qa","country_name":"Qatar","created":"0001-01-01T00:00:00Z","minimum_digits":1000000,"maximum_digits":99999999,"login_channels":["whatsapp"],"currency":"ر.ق","flag":"https://onsite.fra1.cdn.digitaloceanspaces.com/countryflag/Qatar.png","tax_slabs":[0],"tax_display_name":"TIN","tax_value_display_name":"VAT","published":1,"decimal_digit":6,"timezone":"+03:00"},{"country_code":"1","country_iso":"us","country_name":"US / Canada","created":"0001-01-01T00:00:00Z","minimum_digits":1000000000,"maximum_digits":9999999999,"login_channels":["whatsapp","sms"],"currency":"$","flag":"https://onsite.fra1.cdn.digitaloceanspaces.com/countryflag/United-states-of-america.png","tax_slabs":[0,5,11.5],"tax_display_name":"TIN","tax_value_display_name":"VAT","published":1,"decimal_digit":6,"timezone":"-05:00"},{"country_code":"44","country_iso":"gb","country_name":"UK","created":"0001-01-01T00:00:00Z","minimum_digits":1000000000,"maximum_digits":9999999999,"login_channels":["whatsapp"],"currency":"£","flag":"https://onsite.fra1.cdn.digitaloceanspaces.com/countryflag/United-kingdom.png","tax_slabs":[0,5,20],"tax_display_name":"TIN","tax_value_display_name":"VAT","published":1,"decimal_digit":6,"timezone":"+00:00"},{"country_code":"61","country_iso":"au","country_name":"Austraila","created":"0001-01-01T00:00:00Z","minimum_digits":100000000,"maximum_digits":999999999,"login_channels":["whatsapp"],"currency":"A$","flag":"https://onsite.fra1.cdn.digitaloceanspaces.com/countryflag/Australia.png","tax_slabs":[0,10],"tax_display_name":"GST","tax_value_display_name":"GST","published":1,"decimal_digit":6,"timezone":"+10:00"},{"country_code":"965","country_iso":"kw","country_name":"Kuwait","created":"0001-01-01T00:00:00Z","minimum_digits":1000000,"maximum_digits":99999999,"login_channels":["whatsapp"],"currency":"KWD","flag":"https://onsite.fra1.cdn.digitaloceanspaces.com/countryflag/Kuwait.png","tax_slabs":[0,15],"tax_display_name":"TIN","tax_value_display_name":"VAT","published":1,"decimal_digit":6,"timezone":"+03:00"},{"country_code":"968","country_iso":"om","country_name":"Oman","created":"0001-01-01T00:00:00Z","minimum_digits":10000000,"maximum_digits":99999999,"login_channels":["whatsapp"],"currency":"OMR","flag":"https://onsite.fra1.cdn.digitaloceanspaces.com/countryflag/Oman.png","tax_slabs":[0,5,15],"tax_display_name":"VAT","tax_value_display_name":"VAT","published":1,"decimal_digit":6,"timezone":"+04:00"},{"country_code":"62","country_iso":"id","country_name":"Indonesia","created":"0001-01-01T00:00:00Z","minimum_digits":10000000,"maximum_digits":999999999999,"login_channels":["whatsapp"],"currency":"IDR","flag":"https://onsite.fra1.cdn.digitaloceanspaces.com/countryflag/Indonesia.png","tax_slabs":[0,11],"tax_display_name":"VAT","tax_value_display_name":"VAT","published":1,"decimal_digit":6,"timezone":"+07:00"},{"country_code":"66","country_iso":"th","country_name":"Thailand","created":"0001-01-01T00:00:00Z","minimum_digits":100000000,"maximum_digits":9999999999,"login_channels":["whatsapp"],"currency":"THB","flag":"https://onsite.fra1.cdn.digitaloceanspaces.com/countryflag/Thailand.png","tax_slabs":[0,7],"tax_display_name":"VAT","tax_value_display_name":"VAT","published":1,"decimal_digit":6,"timezone":"+07:00"},{"country_code":"63","country_iso":"ph","country_name":"Philippines","created":"0001-01-01T00:00:00Z","minimum_digits":1000000000,"maximum_digits":99999999999,"login_channels":["whatsapp"],"currency":"PHP","flag":"https://onsite.fra1.cdn.digitaloceanspaces.com/countryflag/Philippines.png","tax_slabs":[0,12],"tax_display_name":"VAT","tax_value_display_name":"VAT","published":1,"decimal_digit":6,"timezone":"+08:00"},{"country_code":"961","country_iso":"lb","country_name":"Lebanon","created":"0001-01-01T00:00:00Z","minimum_digits":1000000,"maximum_digits":99999999,"login_channels":["whatsapp"],"currency":"LBP","flag":"https://onsite.fra1.cdn.digitaloceanspaces.com/countryflag/Lebanon.png","tax_slabs":[0,11],"tax_display_name":"VAT","tax_value_display_name":"VAT","published":1,"decimal_digit":6,"timezone":"+02:00"},{"country_code":"20","country_iso":"eg","country_name":"Egypt","created":"0001-01-01T00:00:00Z","minimum_digits":100000000,"maximum_digits":9999999999,"login_channels":["whatsapp"],"currency":"EGP","flag":"https://onsite.fra1.cdn.digitaloceanspaces.com/countryflag/Egypt.png","tax_slabs":[0,14],"tax_display_name":"VAT","tax_value_display_name":"VAT","published":1,"decimal_digit":6,"timezone":"+02:00"},{"country_code":"90","country_iso":"tr","country_name":"Turkey","created":"0001-01-01T00:00:00Z","minimum_digits":1000000000,"maximum_digits":9999999999,"login_channels":["whatsapp"],"currency":"TRY","flag":"https://onsite.fra1.cdn.digitaloceanspaces.com/countryflag/Turkey.png","tax_slabs":[0,18],"tax_display_name":"VAT","tax_value_display_name":"VAT","published":1,"decimal_digit":6,"timezone":"+03:00"},{"country_code":"254","country_iso":"ke","country_name":"Kenya","created":"0001-01-01T00:00:00Z","minimum_digits":100000000,"maximum_digits":9999999999,"login_channels":["whatsapp"],"currency":"KES","flag":"https://onsite.fra1.cdn.digitaloceanspaces.com/countryflag/Kenya.png","tax_slabs":[0,12,16],"tax_display_name":"VAT Number","tax_value_display_name":"VAT","published":1,"decimal_digit":6,"timezone":"+03:00"},{"country_code":"27","country_iso":"za","country_name":"South Africa","created":"0001-01-01T00:00:00Z","minimum_digits":100000000,"maximum_digits":9999999999,"login_channels":["whatsapp"],"currency":"ZAN","flag":"https://onsite.fra1.cdn.digitaloceanspaces.com/countryflag/South_Africa.png","tax_slabs":[0,15],"tax_display_name":"VAT Number","tax_value_display_name":"VAT","published":1,"decimal_digit":6,"timezone":"+02:00"},{"country_code":"234","country_iso":"ng","country_name":"Nigeria","created":"0001-01-01T00:00:00Z","minimum_digits":100000000,"maximum_digits":9999999999,"login_channels":["whatsapp"],"currency":"₦","flag":"https://onsite.fra1.cdn.digitaloceanspaces.com/countryflag/Nigeria.png","tax_slabs":[0,7.5],"tax_display_name":"VAT Number","tax_value_display_name":"VAT","published":1,"decimal_digit":6,"timezone":"+01:00"},{"country_code":"973","country_iso":"bh","country_name":"Behrain","created":"0001-01-01T00:00:00Z","minimum_digits":1000000,"maximum_digits":999999999,"login_channels":["whatsapp"],"currency":".د.ب","flag":"https://onsite.fra1.cdn.digitaloceanspaces.com/countryflag/Bahrain_flag.png","tax_slabs":[0,10],"tax_display_name":"VAT Number","tax_value_display_name":"VAT","published":1,"decimal_digit":6,"timezone":"+03:00"},{"country_code":"228","country_iso":"tg","country_name":"Togo","created":"0001-01-01T00:00:00Z","minimum_digits":100000000,"maximum_digits":9999999999,"login_channels":["whatsapp"],"currency":"XOF","flag":"https://onsite.fra1.cdn.digitaloceanspaces.com/countryflag/Togo.png","tax_slabs":[0,15],"tax_display_name":"VAT Number","tax_value_display_name":"VAT","published":1,"decimal_digit":6,"timezone":"+00:00"},{"country_code":"225","country_iso":"ci","country_name":"Ivory Coast","created":"0001-01-01T00:00:00Z","minimum_digits":100000000,"maximum_digits":9999999999,"login_channels":["whatsapp"],"currency":"CFA","flag":"https://onsite.fra1.cdn.digitaloceanspaces.com/countryflag/Ivory_Coast.jpeg","tax_slabs":[0,18],"tax_display_name":"VAT Number","tax_value_display_name":"VAT","published":1,"decimal_digit":6,"timezone":"+00:00"},{"country_code":"92","country_iso":"pk","country_name":"Pakistan","created":"0001-01-01T00:00:00Z","minimum_digits":1000000000,"maximum_digits":9999999999,"login_channels":["whatsapp"],"currency":"Rs","flag":"https://onsite.fra1.cdn.digitaloceanspaces.com/countryflag/pakistan.png","tax_slabs":[18,12,5,0,9,28,0.1,0.25,1.5,3,6,7.5,14],"tax_display_name":"TAX","tax_value_display_name":"TAX","published":1,"decimal_digit":6,"timezone":"+05:00"},{"country_code":"592","country_iso":"gy","country_name":"Guyana","created":"0001-01-01T00:00:00Z","minimum_digits":1000000,"maximum_digits":999999999,"login_channels":["whatsapp"],"currency":"GY$","flag":"https://onsite.fra1.digitaloceanspaces.com/countryflag/Guyana.png","tax_slabs":[0,14],"tax_display_name":"VAT","tax_value_display_name":"VAT","published":1,"decimal_digit":6,"timezone":"-04:00"},{"country_code":"93","country_iso":"af","country_name":"Afghanistan","created":"0001-01-01T00:00:00Z","minimum_digits":100000000,"maximum_digits":999999999,"login_channels":["whatsapp"],"currency":"AFN","flag":"https://onsite.fra1.cdn.digitaloceanspaces.com/countryflag/Afganistan.png","tax_slabs":[10],"tax_display_name":"VAT","tax_value_display_name":"VAT","published":1,"decimal_digit":2,"timezone":"+04:30"},{"country_code":"256","country_iso":"ug","country_name":"Uganda","created":"0001-01-01T00:00:00Z","minimum_digits":100000000,"maximum_digits":999999999,"login_channels":["whatsapp"],"currency":"UGX","flag":"https://onsite.fra1.cdn.digitaloceanspaces.com/countryflag/Uganda.png","tax_slabs":[0,18],"tax_display_name":"TIN","tax_value_display_name":"VAT","published":1,"decimal_digit":0,"timezone":"+03:00"}]